MANIFEST.in
README.rst
requirements.txt
setup.py
metashield_clean_up/__init__.py
metashield_clean_up/api.py
metashield_clean_up.egg-info/PKG-INFO
metashield_clean_up.egg-info/SOURCES.txt
metashield_clean_up.egg-info/dependency_links.txt
metashield_clean_up.egg-info/not-zip-safe
metashield_clean_up.egg-info/requires.txt
metashield_clean_up.egg-info/top_level.txt