Metadata-Version: 1.1
Name: metashield-clean-up
Version: 0.1.2
Summary: Metashield Clean-up Online API SDK
Home-page: https://github.com/ElevenPaths/metashield-clean-up-sdk-python
Author: Eleven Paths
Author-email: metashield-support@support.elevenpaths.com
License: BSD
Keywords: sdk,api,client,clean-up,metashield
Platform: UNKNOWN
Classifier: Intended Audience :: Developers
Classifier: License :: OSI Approved :: GNU General Public License v3 (GPLv3)
Classifier: Operating System :: OS Independent
Classifier: Programming Language :: Python
Classifier: Programming Language :: Python :: 2.7
Classifier: Programming Language :: Python :: 3.3
Classifier: Programming Language :: Python :: 3.4
Classifier: Programming Language :: Python :: 3.5
Classifier: Programming Language :: Python :: 3.6
